{
	"info": {
		"_postman_id": "573cd298-f015-4130-b694-1ab70f162766",
		"name": "sketter",
		"schema": "https://schema.getpostman.com/json/collection/v2.1.0/collection.json",
		"_exporter_id": "13372724"
	},
	"item": [
		{
			"name": "signup",
			"request": {
				"method": "POST",
				"header": [],
				"body": {
					"mode": "raw",
					"raw": "{\r\n    \"email\": \"huydtse1402231@fpt.edu.vn\",\r\n    \"password\": \"123123\",\r\n    \"confirmPassword\": \"123123\"\r\n}",
					"options": {
						"raw": {
							"language": "json"
						}
					}
				},
				"url": {
					"raw": "http://{{HOST}}:{{PORT}}/api/v1/auth/signup",
					"protocol": "http",
					"host": [
						"{{HOST}}"
					],
					"port": "{{PORT}}",
					"path": [
						"api",
						"v1",
						"auth",
						"signup"
					]
				}
			},
			"response": []
		},
		{
			"name": "signup supplier",
			"request": {
				"method": "POST",
				"header": [],
				"body": {
					"mode": "raw",
					"raw": "{\r\n    \"email\": \"quachkhongtriet@gmail.com\",\r\n    \"password\":\"123123\",\r\n    \"confirmPassword\":\"123123\",\r\n    \"name\":\"Tindev\",\r\n    \"owner\":\"Dương Thanh Huy\",\r\n    \"phone\":\"0387698740\",\r\n    \"address\":\"Hong biết luôn =]]\"\r\n}",
					"options": {
						"raw": {
							"language": "json"
						}
					}
				},
				"url": {
					"raw": "http://{{HOST}}:{{PORT}}/api/v1/auth/signup/supplier",
					"protocol": "http",
					"host": [
						"{{HOST}}"
					],
					"port": "{{PORT}}",
					"path": [
						"api",
						"v1",
						"auth",
						"signup",
						"supplier"
					]
				}
			},
			"response": []
		},
		{
			"name": "login with email password",
			"event": [
				{
					"listen": "prerequest",
					"script": {
						"exec": [
							""
						],
						"type": "text/javascript"
					}
				}
			],
			"request": {
				"method": "POST",
				"header": [],
				"body": {
					"mode": "raw",
					"raw": "{\r\n    \"email\": \"huydtse1402231@fpt.edu.vn\",\r\n    \"password\":\"123123\"\r\n}",
					"options": {
						"raw": {
							"language": "json"
						}
					}
				},
				"url": {
					"raw": "http://{{HOST}}:{{PORT}}/api/v1/auth/login",
					"protocol": "http",
					"host": [
						"{{HOST}}"
					],
					"port": "{{PORT}}",
					"path": [
						"api",
						"v1",
						"auth",
						"login"
					]
				}
			},
			"response": []
		},
		{
			"name": "logout",
			"event": [
				{
					"listen": "prerequest",
					"script": {
						"exec": [
							""
						],
						"type": "text/javascript"
					}
				}
			],
			"request": {
				"method": "POST",
				"header": [],
				"body": {
					"mode": "raw",
					"raw": "",
					"options": {
						"raw": {
							"language": "json"
						}
					}
				},
				"url": {
					"raw": "http://{{HOST}}:{{PORT}}/api/v1/auth/logout",
					"protocol": "http",
					"host": [
						"{{HOST}}"
					],
					"port": "{{PORT}}",
					"path": [
						"api",
						"v1",
						"auth",
						"logout"
					]
				}
			},
			"response": []
		},
		{
			"name": "forgot password - send email (nhập mail thiệt nha)",
			"request": {
				"method": "POST",
				"header": [],
				"body": {
					"mode": "raw",
					"raw": "{\r\n    \"email\": \"huydtse140223@fpt.edu.vn\"\r\n}",
					"options": {
						"raw": {
							"language": "json"
						}
					}
				},
				"url": {
					"raw": "http://{{HOST}}:{{PORT}}/api/v1/user/forgot_password",
					"protocol": "http",
					"host": [
						"{{HOST}}"
					],
					"port": "{{PORT}}",
					"path": [
						"api",
						"v1",
						"user",
						"forgot_password"
					]
				}
			},
			"response": []
		},
		{
			"name": "forgot password - change new password (copy link trong email òi pass vào đây)",
			"request": {
				"method": "PATCH",
				"header": [],
				"body": {
					"mode": "raw",
					"raw": "{\r\n    \"password\":\"123456\",\r\n    \"confirmPassword\":\"123456\"\r\n}",
					"options": {
						"raw": {
							"language": "json"
						}
					}
				},
				"url": {
					"raw": "http://{{HOST}}:{{PORT}}/api/v1/user/reset_password/ad62faea7602aef1ea157e462e5ddacb1b4f2e8109d8b1520cfbf13cb62eceba",
					"protocol": "http",
					"host": [
						"{{HOST}}"
					],
					"port": "{{PORT}}",
					"path": [
						"api",
						"v1",
						"user",
						"reset_password",
						"ad62faea7602aef1ea157e462e5ddacb1b4f2e8109d8b1520cfbf13cb62eceba"
					]
				}
			},
			"response": []
		},
		{
			"name": "get me",
			"protocolProfileBehavior": {
				"disableBodyPruning": true
			},
			"request": {
				"method": "GET",
				"header": [
					{
						"key": "Authorization",
						"value": "Bearer eyJhbGciOiJSUzI1NiIsInR5cCI6IkpXVCJ9.eyJpZCI6ImQ2NzEyNmIzLTc5NDMtNGZkYi04ZjY2LWVlMTE0ZmNhNWM1NCIsImlhdCI6MTY1Nzg3NzA5NywiZXhwIjoxNjY1NjUzMDk3fQ.FKOGjYoq75kQyGajsq2-f2St8sy8g6OE9iFgV_m0nJ5HJZzoXU6AohzCevJ9UkVpZGi2rzzC0OwSMEfO7vSUmA",
						"type": "text",
						"disabled": true
					}
				],
				"body": {
					"mode": "raw",
					"raw": "",
					"options": {
						"raw": {
							"language": "json"
						}
					}
				},
				"url": {
					"raw": "http://{{HOST}}:{{PORT}}/api/v1/user/me",
					"protocol": "http",
					"host": [
						"{{HOST}}"
					],
					"port": "{{PORT}}",
					"path": [
						"api",
						"v1",
						"user",
						"me"
					]
				}
			},
			"response": []
		},
		{
			"name": "update me",
			"request": {
				"method": "PATCH",
				"header": [
					{
						"key": "Authorization",
						"value": "Bearer eyJhbGciOiJSUzI1NiIsInR5cCI6IkpXVCJ9.eyJpZCI6IjY4ZjRhNDRmLTE4OTQtNDMwNy1hMDM1LTU1ZmZlOGZhZjFmYiIsImlhdCI6MTY1NzQzODY2NCwiZXhwIjoxNjY1MjE0NjY0fQ.NQiKZ9jAMJb2nUSMBp7ucWld19IkVp_qeJ-D9X9tvEbOeKTS_2NM9LOS5T2N7TmwNab-kTbaiNOl1Qeai4lMlQ",
						"type": "text",
						"disabled": true
					}
				],
				"body": {
					"mode": "formdata",
					"formdata": [
						{
							"key": "avatar",
							"type": "file",
							"src": "/C:/Users/hautt/Desktop/Screenshot 2022-07-09 232056 - Copy.png"
						},
						{
							"key": "name",
							"value": "Dương Thanh Huy",
							"type": "text"
						},
						{
							"key": "phone",
							"value": "0387698745",
							"type": "text"
						},
						{
							"key": "address",
							"value": "Nhà của Huy",
							"type": "text"
						},
						{
							"key": "gender",
							"value": "Nữ",
							"description": "update for traveler",
							"type": "text"
						},
						{
							"key": "dob",
							"value": "2000-01-13",
							"description": "update for traveler",
							"type": "text"
						},
						{
							"key": "dob",
							"value": "2000/01/13",
							"description": "nhập ngày kiểu này cũng được",
							"type": "text",
							"disabled": true
						},
						{
							"key": "owner",
							"value": "Quách Khổng Triết",
							"description": "update for supplier",
							"type": "text",
							"disabled": true
						}
					]
				},
				"url": {
					"raw": "http://{{HOST}}:{{PORT}}/api/v1/user/me",
					"protocol": "http",
					"host": [
						"{{HOST}}"
					],
					"port": "{{PORT}}",
					"path": [
						"api",
						"v1",
						"user",
						"me"
					]
				}
			},
			"response": []
		},
		{
			"name": "update password",
			"request": {
				"method": "PATCH",
				"header": [
					{
						"key": "Authorization",
						"value": "Bearer eyJhbGciOiJSUzI1NiIsInR5cCI6IkpXVCJ9.eyJpZCI6IjY4ZjRhNDRmLTE4OTQtNDMwNy1hMDM1LTU1ZmZlOGZhZjFmYiIsImlhdCI6MTY1NzQzODY2NCwiZXhwIjoxNjY1MjE0NjY0fQ.NQiKZ9jAMJb2nUSMBp7ucWld19IkVp_qeJ-D9X9tvEbOeKTS_2NM9LOS5T2N7TmwNab-kTbaiNOl1Qeai4lMlQ",
						"type": "text",
						"disabled": true
					}
				],
				"body": {
					"mode": "raw",
					"raw": "{\r\n    \"currentPassword\": \"123456\",\r\n    \"newPassword\": \"123123\",\r\n    \"confirmNewPassword\": \"123123\"\r\n}",
					"options": {
						"raw": {
							"language": "json"
						}
					}
				},
				"url": {
					"raw": "http://{{HOST}}:{{PORT}}/api/v1/user/update_password",
					"protocol": "http",
					"host": [
						"{{HOST}}"
					],
					"port": "{{PORT}}",
					"path": [
						"api",
						"v1",
						"user",
						"update_password"
					]
				}
			},
			"response": []
		},
		{
			"name": "test",
			"protocolProfileBehavior": {
				"disableBodyPruning": true
			},
			"request": {
				"method": "GET",
				"header": [
					{
						"key": "Authorization",
						"value": "",
						"type": "text"
					}
				],
				"body": {
					"mode": "raw",
					"raw": "",
					"options": {
						"raw": {
							"language": "json"
						}
					}
				},
				"url": {
					"raw": "http://{{HOST}}:{{PORT}}/healthcheck",
					"protocol": "http",
					"host": [
						"{{HOST}}"
					],
					"port": "{{PORT}}",
					"path": [
						"healthcheck"
					]
				}
			},
			"response": []
		},
		{
			"name": "init role",
			"protocolProfileBehavior": {
				"disableBodyPruning": true
			},
			"request": {
				"method": "GET",
				"header": [
					{
						"key": "Authorization",
						"value": "",
						"type": "text"
					}
				],
				"body": {
					"mode": "raw",
					"raw": "",
					"options": {
						"raw": {
							"language": "json"
						}
					}
				},
				"url": {
					"raw": "http://{{HOST}}:{{PORT}}/healthcheck",
					"protocol": "http",
					"host": [
						"{{HOST}}"
					],
					"port": "{{PORT}}",
					"path": [
						"healthcheck"
					]
				}
			},
			"response": []
		}
	],
	"auth": {
		"type": "bearer"
	},
	"event": [
		{
			"listen": "prerequest",
			"script": {
				"type": "text/javascript",
				"exec": [
					""
				]
			}
		},
		{
			"listen": "test",
			"script": {
				"type": "text/javascript",
				"exec": [
					""
				]
			}
		}
	],
	"variable": [
		{
			"key": "PORT",
			"value": "3123",
			"type": "string"
		},
		{
			"key": "HOST",
			"value": "localhost",
			"type": "string"
		}
	]
}